chartkick/__init__.py
chartkick/django/__init__.py
chartkick/django/static/chartkick/Chart.bundle.js
chartkick/django/static/chartkick/chartkick.js
chartkick/flask/__init__.py
chartkick/licenses/LICENSE-chart.js.txt
chartkick/licenses/LICENSE-chartjs-adapter-date-fns.txt
chartkick/licenses/LICENSE-chartkick.js.txt
chartkick/licenses/LICENSE-date-fns.txt
chartkick/licenses/LICENSE-kurkle-color.txt
chartkick-1.1.0.dist-info/licenses/LICENSE.txt
chartkick-1.1.0.dist-info/METADATA
chartkick-1.1.0.dist-info/WHEEL
chartkick-1.1.0.dist-info/top_level.txt
chartkick-1.1.0.dist-info/RECORD
