Metadata-Version: 2.4
Name: chartkick
Version: 1.1.0
Summary: Create beautiful JavaScript charts with one line of Python
Author-email: Andrew Kane <andrew@ankane.org>
License: MIT
Project-URL: Homepage, https://github.com/ankane/chartkick.py
Requires-Python: >=3.9
License-File: LICENSE.txt
Dynamic: license-file
